neo3vm-stubs/__init__.pyi
neo3vm_stubs-0.10.1.dist-info/METADATA
neo3vm_stubs-0.10.1.dist-info/WHEEL
neo3vm_stubs-0.10.1.dist-info/top_level.txt
neo3vm_stubs-0.10.1.dist-info/RECORD
