Metadata-Version: 2.1
Name: neo3vm-stubs
Version: 0.10.1
Summary: PEP 561 type stubs for neo3vm
Home-page: UNKNOWN
Maintainer: Erik van den Brink
Maintainer-email: erik@coz.io
License: UNKNOWN
Platform: UNKNOWN
Requires-Dist: neo3vm (==0.10.1)
